eb_to_env/__init__.py
eb_to_env/main.py
elasticbeanstalk_to_env-0.1.dist-info/LICENSE
elasticbeanstalk_to_env-0.1.dist-info/METADATA
elasticbeanstalk_to_env-0.1.dist-info/WHEEL
elasticbeanstalk_to_env-0.1.dist-info/entry_points.txt
elasticbeanstalk_to_env-0.1.dist-info/top_level.txt
elasticbeanstalk_to_env-0.1.dist-info/RECORD
