Metadata-Version: 2.1
Name: elasticbeanstalk-to-env
Version: 0.1
Summary: A simple tool that exports ElasticBeanstalk envrionment variables to a .env file
Home-page: UNKNOWN
Author: Jason DeWitt
Author-email: jason.dewitt@10up.com
License: UNKNOWN
Platform: UNKNOWN
Classifier: Programming Language :: Python :: 3
Classifier: License :: OSI Approved :: MIT License
Classifier: Operating System :: OS Independent
Requires-Dist: Click
Requires-Dist: boto3
Requires-Dist: future
Requires-Dist: future-fstrings
